{"appName":"New York University Press","collectionCode":"nyupress-epubs-site","appUrl":"http://localhost/nyupress-epubs-site","appRoot":"/nyupress-epubs-site","discovery":"http://discovery.dlib.nyu.edu:8080/solr3_discovery/nyupress","readiumCloneFromSource":true,"readiumUrl":"http://localhost:8081","readiumBooksDirectory":"/epub_contentz","readiumRepositoryURL":"git@github.com:elgiovanno/readium-js-viewer.git","readiumDirectory":"/www/sitesz","readiumDirectoryName":"readium-js-viewer","readiumRepositoryBranch":"master","url":"http://localhost/nyupress-epubs-site/details/9780814711774/index.html","id":"9780814711774","coverHref":"epub_content/9780814711774/ops/images/9780814711774.jpg","coverage":"New York, London","date":"1992","handle":"http://hdl.handle.net/2333.1/zgmsbf5k","identifier":"9780814711774","language":"EN","packageUrl":"epub_content/9780814711774","publisher":"New York University Press","thumbHref":"epub_content/9780814711774/ops/images/9780814711774-th.jpg","title":"Adventures of the Mind","timestamp":"2014-05-28T21:29:23.198Z","content":["Natalie Clifford Barney, John Spalding Gatton","New York, London","New York University Press","Adventures of the Mind"],"author":["Natalie Clifford Barney, John Spalding Gatton"],"spell":["Natalie Clifford Barney, John Spalding Gatton","Adventures of the Mind"],"closure":"","css":"<link href='http://localhost/nyupress-epubs-site/css/style.css' rel='stylesheet' type='text/css'>","menus":[],"widgets":{}}